fuzzy_date-0.5.6.dist-info/METADATA
fuzzy_date-0.5.6.dist-info/WHEEL
fuzzy_date-0.5.6.dist-info/licenses/LICENSE
fuzzydate/__init__.py
fuzzydate/fuzzydate.cpython-310-arm-linux-gnueabihf.so
fuzzy_date-0.5.6.dist-info/RECORD
