Metadata-Version: 2.4
Name: fuzzy-date
Version: 0.5.6
Classifier: Development Status :: 4 - Beta
Classifier: Intended Audience :: Developers
Classifier: License :: OSI Approved :: MIT License
Classifier: Operating System :: OS Independent
Classifier: Programming Language :: Rust
Classifier: Programming Language :: Python :: Implementation :: CPython
Classifier: Programming Language :: Python :: Implementation :: PyPy
License-File: LICENSE
Summary: Convert various time strings into datetime objects
Keywords: date,parser,relative,time,strtotime
Author-email: Antti Launiainen <antti@antictools.com>
Requires-Python: >=3.9
Project-URL: Homepage, https://github.com/aldroid1/fuzzy-date
Project-URL: Issues, https://github.com/aldroid1/fuzzy-date/issues
Project-URL: Repository, https://github.com/aldroid1/fuzzy-date.git
